DatapoolVisualizer/__init__.py
DatapoolVisualizer/datapool_viewer.py
DatapoolVisualizer/datapool_visualizer.py
DatapoolVisualizer/plot_controler.py
DatapoolVisualizer/plot_widget.py
DataPoolViewer-1.0.0.dist-info/LICENSE
DataPoolViewer-1.0.0.dist-info/METADATA
DataPoolViewer-1.0.0.dist-info/WHEEL
DataPoolViewer-1.0.0.dist-info/top_level.txt
DataPoolViewer-1.0.0.dist-info/RECORD
