Metadata-Version: 2.1
Name: DataPoolViewer
Version: 1.0.0
Summary: A library intended to provide data visualization tools for PyDataCore.
Home-page: https://github.com/yourusername/DataPoolViewer
Author: Guillaume Train
Author-email: g.train@live.fr
Classifier: Programming Language :: Python :: 3
Classifier: License :: OSI Approved :: MIT License
Classifier: Operating System :: OS Independent
Requires-Python: >=3.10
License-File: LICENSE
Requires-Dist: numpy >=1.21
Requires-Dist: pandas >=1.3
Requires-Dist: termcolor ~=2.5.0
Requires-Dist: scipy >=1.7
Requires-Dist: pyqtgraph >=0.12
Requires-Dist: PySide6 >=6.2
Requires-Dist: setuptools ~=75.2.0
Requires-Dist: pytz ~=2024.2
Requires-Dist: six ~=1.16.0
Requires-Dist: tzdata ~=2024.2
Requires-Dist: python-dateutil ~=2.9.0.post0
Requires-Dist: tabulate ~=0.9.0
